hippox/__init__.py
hippox/basis_measures.py
hippox/diagonalization.py
hippox/main.py
hippox-0.0.9.dist-info/LICENSE
hippox-0.0.9.dist-info/METADATA
hippox-0.0.9.dist-info/WHEEL
hippox-0.0.9.dist-info/top_level.txt
hippox-0.0.9.dist-info/RECORD
