Metadata-Version: 2.1
Name: hippox
Version: 0.0.9
Summary: High-order Polynomial Projection Operators (HiPPO) for JAX
Home-page: https://github.com/JPGoodale/hippox
Author: Jacob Goodale
Author-email: goodalejacob@gmail.com
Classifier: Programming Language :: Python :: 3
Classifier: License :: OSI Approved :: MIT License
Classifier: Operating System :: OS Independent
Requires-Python: >=3.7
License-File: LICENSE
